smashbenchmarking/__init__.py
smashbenchmarking/bench.py
smashbenchmarking/compare_callsets.py
smashbenchmarking/identifycancel.py
smashbenchmarking/normalize_vcf.py
smashbenchmarking/vcf_check.py
smashbenchmarking/corrupt/__init__.py
smashbenchmarking/corrupt/base51.py
smashbenchmarking/corrupt/bubble.py
smashbenchmarking/corrupt/contaminate.py
smashbenchmarking/parsers/__init__.py
smashbenchmarking/parsers/genome.py
smashbenchmarking/parsers/util.py
smashbenchmarking/parsers/vcfwriter.py
smashbenchmarking/vcf_eval/__init__.py
smashbenchmarking/vcf_eval/callset_helper.py
smashbenchmarking/vcf_eval/chrom_variants.py
smashbenchmarking/vcf_eval/eval_helper.py
smashbenchmarking/vcf_eval/rectify_seq.py
smashbenchmarking/vcf_eval/variants.py
smashbenchmarking-1.0.1.dist-info/DESCRIPTION.rst
smashbenchmarking-1.0.1.dist-info/METADATA
smashbenchmarking-1.0.1.dist-info/metadata.json
smashbenchmarking-1.0.1.dist-info/RECORD
smashbenchmarking-1.0.1.dist-info/top_level.txt
smashbenchmarking-1.0.1.dist-info/WHEEL
