Metadata-Version: 2.0
Name: smashbenchmarking
Version: 1.0.1
Summary: Check the accuracy of one VCF callset against another
Home-page: http://github.com/amplab/smash/
Author: AMPlab, UC Berkeley
Author-email: smashbenchmarking@googlegroups.com
License: BSD
Platform: UNKNOWN
Classifier: Development Status :: 4 - Beta
Classifier: Intended Audience :: Developers
Classifier: Intended Audience :: Science/Research
Classifier: Natural Language :: English
Classifier: License :: OSI Approved :: BSD License
Classifier: Operating System :: OS Independent
Classifier: Programming Language :: Python
Classifier: Programming Language :: Python :: 2
Classifier: Programming Language :: Python :: 2.6
Classifier: Programming Language :: Python :: 2.7
Classifier: Programming Language :: Python :: 3
Classifier: Programming Language :: Python :: 3.3
Classifier: Topic :: Scientific/Engineering :: Bio-Informatics
Requires-Dist: pyvcf
Requires-Dist: pyfasta
Requires-Dist: numpy
